rqdatac_risk_model/__init__.py
rqdatac_risk_model/_version.py
rqdatac_risk_model/api.py
rqdatac_risk_model-0.1.2.dist-info/METADATA
rqdatac_risk_model-0.1.2.dist-info/WHEEL
rqdatac_risk_model-0.1.2.dist-info/top_level.txt
rqdatac_risk_model-0.1.2.dist-info/RECORD
