Metadata-Version: 2.4
Name: rqdatac_risk_model
Version: 0.1.2
Summary: Project Short Description
Author-email: Ricequant <public@ricequant.com>
Project-URL: Homepage, https://www.ricequant.com/
Keywords: rqdatac_risk_model
Classifier: Programming Language :: Python :: 3
Classifier: Programming Language :: Python :: 3.7
Classifier: Programming Language :: Python :: 3.8
Classifier: Programming Language :: Python :: 3.9
Classifier: Programming Language :: Python :: 3.10
Classifier: Programming Language :: Python :: 3.11
Classifier: Programming Language :: Python :: 3.12
Classifier: Programming Language :: Python :: 3.13
Classifier: Intended Audience :: Developers
Classifier: Operating System :: OS Independent
Classifier: Environment :: Console
Requires-Python: >=3.7
Requires-Dist: rqdatac
